core_mixins/__init__.py
core_mixins/compatibility.py
core_mixins/exceptions.py
core_mixins/logger.py
core_mixins/py.typed
core_mixins/utils.py
core_mixins/decorators/__init__.py
core_mixins/decorators/async_.py
core_mixins/decorators/cache.py
core_mixins/decorators/count_calls.py
core_mixins/decorators/repeat.py
core_mixins/decorators/retry.py
core_mixins/decorators/singleton.py
core_mixins/decorators/timer.py
core_mixins/files/__init__.py
core_mixins/files/utils.py
core_mixins/interfaces/__init__.py
core_mixins/interfaces/factory.py
core_mixins/interfaces/task.py
core_mixins/managers/__init__.py
core_mixins/managers/tasks_manager.py
core_mixins-2.2.4.dist-info/licenses/LICENSE
core_mixins-2.2.4.dist-info/METADATA
core_mixins-2.2.4.dist-info/WHEEL
core_mixins-2.2.4.dist-info/top_level.txt
core_mixins-2.2.4.dist-info/RECORD
