Metadata-Version: 2.4
Name: core-mixins
Version: 2.2.4
Summary: This project contains common and generic functions, decorators, interfaces and classes...
Author-email: Alejandro Cora González <alek.cora.glez@gmail.com>
Maintainer: Alejandro Cora González
License-Expression: MIT
Project-URL: Homepage, https://gitlab.com/bytecode-solutions/core/core-mixins
Project-URL: Repository, https://gitlab.com/bytecode-solutions/core/core-mixins
Project-URL: Documentation, https://core-mixins.readthedocs.io/en/latest/
Project-URL: Issues, https://gitlab.com/bytecode-solutions/core/core-mixins/-/issues
Project-URL: Changelog, https://gitlab.com/bytecode-solutions/core/core-mixins/-/blob/master/CHANGELOG.md
Classifier: Intended Audience :: Developers
Classifier: Development Status :: 5 - Production/Stable
Classifier: Topic :: Software Development :: Libraries :: Python Modules
Classifier: Topic :: Utilities
Classifier: Programming Language :: Python :: 3
Classifier: Programming Language :: Python :: 3 :: Only
Classifier: Programming Language :: Python :: 3.9
Classifier: Programming Language :: Python :: 3.10
Classifier: Programming Language :: Python :: 3.11
Classifier: Programming Language :: Python :: 3.12
Classifier: Programming Language :: Python :: 3.13
Requires-Python: >=3.9
License-File: LICENSE
Requires-Dist: core-tests>=2.0.1
Requires-Dist: typing-extensions>=4.8.0; python_version >= "3.9" and python_version < "3.11"
Provides-Extra: dev
Requires-Dist: core-dev-tools>=1.0.1; extra == "dev"
Dynamic: license-file
